Metadata-Version: 2.1
Name: LAPCA
Version: 0.0.2
Summary: LAPCA is a tool that is used to check whether the given program conforms to the specified guidelines. 
Home-page: 
Author: Swaroop Bhat
Author-email: swaroopbhat510@gmail.com
License: MIT
Keywords: Conformance,language agnostic,program,guidelines,LAPCA,LAPCA Score
Classifier: Development Status :: 5 - Production/Stable
Classifier: Intended Audience :: Developers
Classifier: Intended Audience :: Education
Classifier: Intended Audience :: Information Technology
Classifier: Operating System :: Microsoft :: Windows :: Windows 10 
Classifier: Operating System :: Microsoft :: Windows :: Windows 11 
Classifier: Operating System :: POSIX :: Linux
Classifier: License :: OSI Approved :: MIT License
Classifier: Programming Language :: Python :: 3
License-File: LICENSE.txt
